README.md
cytolysis/__init__.py
cytolysis/anutils.py
cytolysis/aster.py
cytolysis/couples.py
cytolysis/cytosim_analysis.py
cytolysis/fibers.py
cytolysis/objects.py
cytolysis/read_config.py
cytolysis/example_data/couples_states.txt
cytolysis/example_data/example.cym
cytolysis/example_data/fiber_points.txt
cytolysis/example_data/fibers.txt
cytolysis/example_data/solids.txt
cytolysis/example_data/space.txt
cytolysis-0.0.36.dist-info/LICENSE
cytolysis-0.0.36.dist-info/METADATA
cytolysis-0.0.36.dist-info/WHEEL
cytolysis-0.0.36.dist-info/top_level.txt
cytolysis-0.0.36.dist-info/RECORD
