Metadata-Version: 2.1
Name: cytolysis
Version: 0.0.36
Summary: An API to analyze cytosim simulations
Home-page: https://gitlab.com/SergeDmi/cytosim_analysis
Author: Serge Dmitrieff
License: UNKNOWN
Platform: UNKNOWN
Requires-Dist: numpy
Requires-Dist: pandas
